fasttask_manager/__init__.py
fasttask_manager/async_manager.py
fasttask_manager/create_project.py
fasttask_manager/manager.py
fasttask_manager/project/Dockerfile
fasttask_manager/project/docker-compose.yml
fasttask_manager/project/requirements.txt
fasttask_manager/project/setting.py
fasttask_manager/project/tasks/get_hypotenuse.py
fasttask_manager/project/tasks/packages/tools.py
fasttask_manager-0.4.0.dist-info/licenses/LICENSE
fasttask_manager-0.4.0.dist-info/METADATA
fasttask_manager-0.4.0.dist-info/WHEEL
fasttask_manager-0.4.0.dist-info/top_level.txt
fasttask_manager-0.4.0.dist-info/RECORD
