Metadata-Version: 2.4
Name: fasttask_manager
Version: 0.4.0
Summary: fasttask's manager 
Home-page: https://github.com/iridesc/fasttask_manager
Author: Irid
Author-email: irid.zzy@gmail.com
Classifier: Programming Language :: Python :: 3
Classifier: License :: OSI Approved :: MIT License
Classifier: Operating System :: OS Independent
License-File: LICENSE
Requires-Dist: retry
Requires-Dist: requests
Requires-Dist: httpx
Requires-Dist: tenacity
Dynamic: author
Dynamic: author-email
Dynamic: classifier
Dynamic: description
Dynamic: description-content-type
Dynamic: home-page
Dynamic: license-file
Dynamic: requires-dist
Dynamic: summary
